cpkmodel/__init__.py
cpkmodel/compositekey.py
cpkmodel/constants.py
cpkmodel/cpkmodel.py
cpkmodel/cpkquery.py
django_compositepk_model-1.0.3.dist-info/METADATA
django_compositepk_model-1.0.3.dist-info/WHEEL
django_compositepk_model-1.0.3.dist-info/licenses/LICENSE
django_compositepk_model-1.0.3.dist-info/RECORD
