Metadata-Version: 2.3
Name: django-compositepk-model
Version: 1.0.3
Summary: Extended Django Model class with composite-primary-key support
Project-URL: Homepage, https://github.com/Arisophy/django-compositepk-model
Project-URL: Repository, https://github.com/Arisophy/django-compositepk-model.git
Project-URL: Issues, https://github.com/Arisophy/django-compositepk-model/issues
Author-email: Arisophy <arisophy@is-jpn.com>
License: MIT License
License-File: LICENSE
Keywords: Multi-Column Primary Key,composite primary keys,django,django-admin,model
Classifier: Development Status :: 5 - Production/Stable
Classifier: Intended Audience :: Developers
Classifier: License :: OSI Approved :: MIT License
Classifier: Operating System :: OS Independent
Classifier: Programming Language :: Python :: 3
Classifier: Programming Language :: Python :: 3.6
Classifier: Programming Language :: Python :: 3.7
Classifier: Programming Language :: Python :: 3.8
Classifier: Programming Language :: Python :: 3.9
Requires-Python: >=3.6
Requires-Dist: django>=3.2
